lvlup/lvlup.py
lvlup-1.0.dist-info/DESCRIPTION.rst
lvlup-1.0.dist-info/METADATA
lvlup-1.0.dist-info/metadata.json
lvlup-1.0.dist-info/RECORD
lvlup-1.0.dist-info/top_level.txt
lvlup-1.0.dist-info/WHEEL
