Metadata-Version: 2.0
Name: lvlup
Version: 1.0
Summary: Leveling up from the command line
Home-page: http://github.com/keithalpichi/lvlup
Author: Keith Alpichi
Author-email: info@keithalpichi.com
License: MIT
Keywords: afplay audio sound play music
Platform: UNKNOWN
Classifier: Programming Language :: Python :: 2 :: Only
Requires-Dist: afplay
